feature_engineering_rs-0.2.96.dist-info/METADATA
feature_engineering_rs-0.2.96.dist-info/WHEEL
feature_engineering_rs-0.2.96.dist-info/licenses/LICENSE
feature_engineering_rs/__init__.py
feature_engineering_rs/feature_engineering_rs.cpython-313-darwin.so
feature_engineering_rs-0.2.96.dist-info/RECORD
