Metadata-Version: 2.4
Name: feature-engineering-rs
Version: 0.2.96
Classifier: Programming Language :: Rust
Classifier: Programming Language :: Python :: Implementation :: CPython
Classifier: Programming Language :: Python :: Implementation :: PyPy
License-File: LICENSE
Summary: A high-performance feature engineering package built with Rust and exposed to Python via PyO3
Keywords: feature-engineering,time-series,rust,performance
Author-email: Carlos Arias <carlos.eligio92@gmail.com>
License: MIT
Requires-Python: >=3.8
